wb_api/__init__.py
wb_api/async_api.py
wb_api/const.py
wb_api/exception.py
wb_api/sync_api.py
wb_api/base/__init__.py
wb_api/base/api.py
wb_api/base/async_api_mixin.py
wb_api/base/async_config.py
wb_api/base/config.py
wb_api/base/router.py
wb_api/base/sync_api_mixin.py
wb_api/base/sync_config.py
wb_api/base/dataclass/__init__.py
wb_api/base/dataclass/base_request.py
wb_api/base/dataclass/base_response.py
wb_api/base/dataclass/ping.py
wb_api/common/__init__.py
wb_api/common/async_api.py
wb_api/common/base_api.py
wb_api/common/router.py
wb_api/common/sync_api.py
wb_api/feedback/__init__.py
wb_api/feedback/async_api.py
wb_api/feedback/base_api.py
wb_api/feedback/const.py
wb_api/feedback/router.py
wb_api/feedback/sync_api.py
wb_api/feedback/dataclass/__init__.py
wb_api/feedback/dataclass/feedback.py
wb_api/feedback/dataclass/feedback_answer_add.py
wb_api/feedback/dataclass/feedback_answer_update.py
wb_api/feedback/dataclass/feedback_archive_list.py
wb_api/feedback/dataclass/feedback_count.py
wb_api/feedback/dataclass/feedback_count_unanswered.py
wb_api/feedback/dataclass/feedback_get.py
wb_api/feedback/dataclass/feedback_list.py
wb_api/feedback/dataclass/feedback_order_return.py
wb_api/feedback/dataclass/feedback_product_report.py
wb_api/feedback/dataclass/feedback_supplier_valuations.py
wb_api/feedback/dataclass/feedback_text_report.py
wb_api/feedback/dataclass/new_feedbacks_questions.py
wb_api/feedback/dataclass/question.py
wb_api/feedback/dataclass/question_answer_add.py
wb_api/feedback/dataclass/question_answer_update.py
wb_api/feedback/dataclass/question_count.py
wb_api/feedback/dataclass/question_count_unanswered.py
wb_api/feedback/dataclass/question_get.py
wb_api/feedback/dataclass/question_list.py
wb_api/feedback/dataclass/question_mark_as_read.py
wb_api/feedback/dataclass/question_reject.py
wb_api/generic/__init__.py
wb_api/generic/functools.py
wb_api/generic/requests/__init__.py
wb_api/generic/requests/auth.py
wildberries_api-2.0.0.dist-info/METADATA
wildberries_api-2.0.0.dist-info/WHEEL
wildberries_api-2.0.0.dist-info/licenses/LICENSE
wildberries_api-2.0.0.dist-info/RECORD
